pg_mongodb/__init__.py
pg_mongodb/define.py
pg_mongodb/mongo.py
pg_mongodb-1.0.5.dist-info/METADATA
pg_mongodb-1.0.5.dist-info/WHEEL
pg_mongodb-1.0.5.dist-info/top_level.txt
pg_mongodb-1.0.5.dist-info/RECORD
